ikaris/__init__.py
ikaris/main.py
ikaris/checker/__init__.py
ikaris/checker/dependencies_verification.py
ikaris/checker/file_verification.py
ikaris/checker/model_card_verification.py
ikaris/checker/source_verification.py
ikaris/checker/vulnerability_verification.py
ikaris/helpers/__init__.py
ikaris/helpers/logging.py
ikaris-0.2.1.dist-info/licenses/LICENSE
ikaris-0.2.1.dist-info/METADATA
ikaris-0.2.1.dist-info/WHEEL
ikaris-0.2.1.dist-info/entry_points.txt
ikaris-0.2.1.dist-info/top_level.txt
ikaris-0.2.1.dist-info/RECORD
