Metadata-Version: 2.4
Name: ikaris
Version: 0.2.1
Summary: Ikaris - Open-source Hugging Face model & python package safety checker
Author-email: Haydar Miezanie Abdul Jamil <haydarsaja@gmail.com>
License: Apache 2.0
Project-URL: Homepage, https://github.com/haydarmiezanie/ikaris
Project-URL: Repository, https://github.com/haydarmiezanie/ikaris
Project-URL: Bug_Tracker, https://github.com/haydarmiezanie/ikaris/issues
Keywords: huggingface,python package,security,model & package scanner,AI safety,clean package
Requires-Python: >=3.8
License-File: LICENSE
Requires-Dist: huggingface_hub
Requires-Dist: colorama
Requires-Dist: requests
Dynamic: license-file
